nbss_upload.py
nbss_upload-0.1.dist-info/LICENSE
nbss_upload-0.1.dist-info/METADATA
nbss_upload-0.1.dist-info/WHEEL
nbss_upload-0.1.dist-info/entry_points.txt
nbss_upload-0.1.dist-info/top_level.txt
nbss_upload-0.1.dist-info/RECORD
