Metadata-Version: 2.1
Name: nbss-upload
Version: 0.1
Summary: Upload notebooks to a notebooksharing.space instance
Home-page: https://github.com/notebook-sharing-space/nbss-upload
Author: Yuvi Panda
Author-email: yuvipanda@gmail.com
License: 3-clause BSD
Platform: any
License-File: LICENSE
Requires-Dist: requests
